{
  "UUID": "84d0e973-dc14-330c-9c0e-e54f8f7bfd7b",
  "_displayName_": "Resources",
  "_keyword_": "e_learning_component",
  "allowReview": false,
  "created": "2015-05-04 17:04:56",
  "createdById": 3,
  "deprecatedBy": "",
  "generateCertificate": "DEFAULT",
  "generateProofOfCompletion": "DEFAULT",
  "id": 169,
  "launchWithScooter": false,
  "learndotCourse": 2417,
  "learndotDomain": "puppetlabs.learndot.com",
  "maxAttempts": -1,
  "modified": "2016-07-05 11:52:06",
  "modifiedById": 38,
  "name": "Resources",
  "orderNumber": 3,
  "price": "0.0 USD",
  "primaryCategoryId": 7,
  "status": "ENABLED",
  "urlName": "resources",
  "visibility": "PUBLIC",
  "duration.minutesPerDay": 10,
  "duration.days": 0
}