{"UUID":"a5e85184-3da8-37de-bb03-761713a2c80f","_displayName_":"04. Puppet Firewalls- Action Items & Resources","_keyword_":"content_component","created":"2015-02-04 14:23:06","createdById":3,"deprecatedBy":"","duration":{"days":0,"minutesPerDay":0},"generateCertificate":"DEFAULT","generateProofOfCompletion":"DEFAULT","id":137,"modified":"2015-02-04 14:23:06","modifiedById":3,"name":"04. Puppet Firewalls- Action Items & Resources","orderNumber":0,"price":{"amount":0.0,"currency":"USD"},"primaryCategoryId":1,"providerId":1,"status":"ACTIVE_COMPONENT","urlName":"04-puppet-firewalls--action-items-resources","visibility":"HIDDEN"}