{
  "_displayName_": "Getting Started with Hiera",
  "_keyword_": "course_pathway",
  "courseInfo": "",
  "created": "2016-07-13 11:45:56",
  "createdById": 35,
  "deprecatedBy": "",
  "generateCertificate": "DEFAULT",
  "generateProofOfCompletion": "DEFAULT",
  "modified": "2016-11-16 11:30:11",
  "modifiedById": 35,
  "name": "Getting Started with Hiera",
  "orderNumber": 0,
  "price": "0.0 USD",
  "primaryCategoryId": 7,
  "status": "ENABLED",
  "type": {
    "_displayName_": "Course",
    "_keyword_": "course_pathway_type",
    "created": "2015-06-14 23:21:43",
    "id": 4,
    "modified": "2015-06-14 23:21:43",
    "name": "Course",
    "rootType": true,
    "supportedComponentTypes": [
      "e_learning_component",
      "course",
      "content_component",
      "exam_component"
    ]
  },
  "typeId": 4,
  "urlName": "getting-started-with-hiera",
  "visibility": "PUBLIC",
  "duration.minutesPerDay": 0,
  "duration.days": 0
}